zoom_meeting_sdk.libs/libatomic-1d7ed5db.so.1.2.0
zoom_meeting_sdk.libs/libgbm-8c5afaed.so.1.0.0
zoom_meeting_sdk.libs/libgio-2-d22b4047.0.so.0.5600.4
zoom_meeting_sdk.libs/libuuid-95b83d40.so.1.3.0
zoom_meeting_sdk.libs/libQt5Qml-ee4cc8ae.so.5
zoom_meeting_sdk.libs/libmeetingsdk-e48ab9d3.so.1
zoom_meeting_sdk.libs/libmount-ec61bd71.so.1.1.0
zoom_meeting_sdk.libs/libdbus-1-79ebe1c2.so.3.19.7
zoom_meeting_sdk.libs/libicudata-2860f210.so.56
zoom_meeting_sdk.libs/libicui18n-5ecff006.so.56
zoom_meeting_sdk.libs/libQt5Quick-e2870380.so.5
zoom_meeting_sdk.libs/libgssapi_krb5-9b4a36a0.so.2.2
zoom_meeting_sdk.libs/libQt5Gui-d8108175.so.5
zoom_meeting_sdk.libs/libffi-3a37023a.so.6.0.2
zoom_meeting_sdk.libs/libxcb-shm-0be6dfbf.so.0.0.0
zoom_meeting_sdk.libs/libcrypto-401bea5d.so.1.1.1k
zoom_meeting_sdk.libs/libXau-154567c4.so.6.0.0
zoom_meeting_sdk.libs/libkrb5-01ecc178.so.3.3
zoom_meeting_sdk.libs/libpcre2-8-516f4c9d.so.0.7.1
zoom_meeting_sdk.libs/libxcb-xfixes-6de855b8.so.0.0.0
zoom_meeting_sdk.libs/libdrm-b0291a67.so.2.4.0
zoom_meeting_sdk.libs/libicuuc-9ee010e3.so.56
zoom_meeting_sdk.libs/libxcb-5ddf6756.so.1.1.0
zoom_meeting_sdk.libs/libcom_err-b4375b23.so.2.1
zoom_meeting_sdk.libs/libQt5QmlModels-511e2cf7.so.5
zoom_meeting_sdk.libs/libxcb-shape-7716c890.so.0.0.0
zoom_meeting_sdk.libs/libpcre-0dd207b5.so.1.2.10
zoom_meeting_sdk.libs/libxcb-xtest-b1ab725e.so.0.0.0
zoom_meeting_sdk.libs/libselinux-64a010fa.so.1
zoom_meeting_sdk.libs/libQt5Network-7e6a5597.so.5
zoom_meeting_sdk.libs/libkeyutils-2777d33d.so.1.6
zoom_meeting_sdk.libs/libxcb-randr-562554c2.so.0.1.0
zoom_meeting_sdk.libs/libQt5Core-2205c39c.so.5
zoom_meeting_sdk.libs/libkrb5support-4699da94.so.0.1
zoom_meeting_sdk.libs/libblkid-a9167753.so.1.1.0
zoom_meeting_sdk.libs/libxcb-util-9255dd30.so.1.0.0
zoom_meeting_sdk.libs/libXfixes-e3b7d94c.so.3.1.0
zoom_meeting_sdk.libs/libwayland-server-db937297.so.0.21.0
zoom_meeting_sdk.libs/libgmodule-2-d601e47e.0.so.0.5600.4
zoom_meeting_sdk-0.0.25.dist-info/WHEEL
zoom_meeting_sdk-0.0.25.dist-info/METADATA
zoom_meeting_sdk-0.0.25.dist-info/RECORD
