Metadata-Version: 2.1
Name: zoom-meeting-sdk
Version: 0.0.25
Summary: Python Bindings for the Zoom Meeting SDK
Author-Email: Noah Duncan <nduncan@hmc.edu>
Classifier: License :: OSI Approved :: BSD License
Classifier: Programming Language :: Python :: 3.10
Classifier: Programming Language :: Python :: 3.11
Classifier: Programming Language :: Python :: 3.12
Classifier: Programming Language :: Python :: 3.13
Classifier: Programming Language :: Python :: 3.14
Classifier: Development Status :: 4 - Beta
Project-URL: Homepage, https://github.com/noah-duncan/py-zoom-meeting-sdk
Requires-Python: >=3.10
